tbk/__init__.py
tbk/__main__.py
tbk/cmd/init.py
tbk/cmd/show.py
tbk/cmd/status.py
tbk/logic/card.py
tbk/logic/consts.py
tbk/logic/get_card.py
tbk/logic/repeater.py
TextBasedKanban-0.0.0a1.dist-info/LICENSE
TextBasedKanban-0.0.0a1.dist-info/METADATA
TextBasedKanban-0.0.0a1.dist-info/WHEEL
TextBasedKanban-0.0.0a1.dist-info/entry_points.txt
TextBasedKanban-0.0.0a1.dist-info/top_level.txt
TextBasedKanban-0.0.0a1.dist-info/RECORD
