Metadata-Version: 2.1
Name: TextBasedKanban
Version: 0.0.0a1
Summary: Vaguely git-flavored text-based Kanban board management.
Author-email: AbyxDev <ken@abyx.dev>
Project-URL: Homepage, https://github.com/Kenny2github/TextBasedKanban
Project-URL: Bug Tracker, https://github.com/Kenny2github/TextBasedKanban/issues
Requires-Python: >=3.10
License-File: LICENSE
Requires-Dist: PyYAML
Requires-Dist: rich
Provides-Extra: test
Requires-Dist: pytest ~=7.0 ; extra == 'test'
